seg/__init__.py
seg/losses.py
seg/metrics.py
seg/models/__init__.py
seg/models/base.py
seg/models/decoders.py
seg/models/encoders.py
seg/utils/__init__.py
seg/utils/data.py
seg_anushqaa-0.1.0.dist-info/licenses/LICENSE
seg_anushqaa-0.1.0.dist-info/METADATA
seg_anushqaa-0.1.0.dist-info/WHEEL
seg_anushqaa-0.1.0.dist-info/top_level.txt
seg_anushqaa-0.1.0.dist-info/RECORD
