Metadata-Version: 2.4
Name: seg-anushqaa
Version: 0.1.0
Summary: A modular TensorFlow/Keras Image segmentation library
Author-email: Anushqaa <anushqa.shekhawat@gmail.com>
License: MIT
Keywords: segmentation,tensorflow,keras,deeplab,unet
Classifier: Programming Language :: Python :: 3
Classifier: License :: OSI Approved :: MIT License
Classifier: Operating System :: OS Independent
License-File: LICENSE
Requires-Dist: tensorflow>=2.10
Requires-Dist: numpy
Dynamic: license-file
